{
  "id": "ORD_1758778619_89",
  "customer_email": "procurement@siemens.com",
  "customer_name": "Siemens AG",
  "items": [
    {
      "sku": "BTN-TECH-301",
      "name": "Tech Series Smart Button",
      "quantity": 208,
      "unit_price": 15.5,
      "total_price": 3224.0
    },
    {
      "sku": "BTN-IND-201",
      "name": "Industrial Heavy Duty Button",
      "quantity": 872,
      "unit_price": 4.2,
      "total_price": 3662.4
    }
  ],
  "total_amount": 6886.4,
  "priority": 2,
  "sla_hours": 12,
  "current_state": "CLOSED",
  "created_at": 1757054219.331747,
  "history": [
    {
      "from_state": "CREATED",
      "to_state": "CREATED",
      "timestamp": 1758778619.906309,
      "agent": "OrderSystem",
      "reason": "Order created from email/PDF",
      "metadata": {
        "source": "email_processing",
        "total_amount": 6886.4
      }
    },
    {
      "from_state": "CREATED",
      "to_state": "CONFIRMED",
      "timestamp": 1758778619.9065824,
      "agent": "SalesAgent",
      "reason": "Customer confirmed order via email",
      "metadata": {
        "simulation_generated": true,
        "timestamp": 1757056969.7306392,
        "confirmation_method": "portal_confirmation",
        "delivery_address": "Main Plant",
        "special_instructions": null
      }
    },
    {
      "from_state": "CONFIRMED",
      "to_state": "PLANNED",
      "timestamp": 1758778619.907161,
      "agent": "ProductionPlanning",
      "reason": "Production scheduled and materials reserved",
      "metadata": {
        "simulation_generated": true,
        "timestamp": 1757097412.7458284,
        "production_slot": "2025-01-12 13:00",
        "assigned_line": "Special Line",
        "estimated_duration": "56 hours"
      }
    },
    {
      "from_state": "PLANNED",
      "to_state": "IN_PRODUCTION",
      "timestamp": 1758778619.9077315,
      "agent": "ProductionAgent",
      "reason": "Manufacturing commenced",
      "metadata": {
        "simulation_generated": true,
        "timestamp": 1757130765.859453,
        "batch_number": "BATCH_2025_856",
        "quality_inspector": "Hans Weber",
        "materials_reserved": true,
        "production_notes": "Extra QC required"
      }
    },
    {
      "from_state": "IN_PRODUCTION",
      "to_state": "PRODUCED",
      "timestamp": 1758778619.9083915,
      "agent": "QualityInspector",
      "reason": "Quality inspection passed",
      "metadata": {
        "simulation_generated": true,
        "timestamp": 1757134849.7409546,
        "qa_inspector": "Thomas Klein",
        "quality_score": "B+",
        "defect_rate": "0.084%",
        "batch_test_results": "PASSED"
      }
    },
    {
      "from_state": "PRODUCED",
      "to_state": "PACKED",
      "timestamp": 1758778619.9090285,
      "agent": "LogisticsAgent",
      "reason": "Order packed and labeled",
      "metadata": {
        "simulation_generated": true,
        "timestamp": 1757136707.9403517,
        "package_id": "PKG_2025_8894",
        "weight_kg": 17.4,
        "dimensions": "57x39x28cm",
        "packaging_type": "Reinforced Box"
      }
    },
    {
      "from_state": "PACKED",
      "to_state": "SHIPPED",
      "timestamp": 1758778619.909689,
      "agent": "ShippingCoordinator",
      "reason": "Shipped via DHL Express",
      "metadata": {
        "simulation_generated": true,
        "timestamp": 1757158209.2135468,
        "tracking_number": "DHL906994473",
        "carrier": "DHL Standard",
        "shipping_cost": 45.49,
        "estimated_delivery": "2025-01-30"
      }
    },
    {
      "from_state": "SHIPPED",
      "to_state": "DELIVERED",
      "timestamp": 1758778619.910362,
      "agent": "LogisticsAgent",
      "reason": "Delivery confirmed by recipient",
      "metadata": {
        "simulation_generated": true,
        "timestamp": 1757308274.6142073,
        "delivery_timestamp": "2025-01-25 17:41",
        "recipient": "Receiving Dept",
        "signature": "K. Weber"
      }
    },
    {
      "from_state": "DELIVERED",
      "to_state": "INVOICED",
      "timestamp": 1758778619.911023,
      "agent": "AccountsReceivable",
      "reason": "Invoice generated and sent",
      "metadata": {
        "simulation_generated": true,
        "timestamp": 1757321549.347097,
        "invoice_number": "INV-2025-3446",
        "payment_terms": "Net 14",
        "discount_applied": 0
      }
    },
    {
      "from_state": "INVOICED",
      "to_state": "CLOSED",
      "timestamp": 1758778619.9116952,
      "agent": "FinanceAgent",
      "reason": "Payment received and processed",
      "metadata": {
        "simulation_generated": true,
        "timestamp": 1759616825.3224285,
        "payment_date": "2025-2-21",
        "payment_method": "Bank Transfer",
        "transaction_id": "TXN_766629"
      }
    }
  ],
  "metadata": {
    "customer_type": "Enterprise",
    "simulation_day": 11,
    "historical_seed": true,
    "original_timestamp": 1757054219.331747
  }
}