{
  "id": "ORD_1758778620_191",
  "customer_email": "orders@mahle.com",
  "customer_name": "MAHLE GmbH",
  "items": [
    {
      "sku": "BTN-STD-102",
      "name": "Standard White Button",
      "quantity": 1293,
      "unit_price": 1.5,
      "total_price": 1939.5
    },
    {
      "sku": "BTN-STD-102",
      "name": "Standard White Button",
      "quantity": 140,
      "unit_price": 1.5,
      "total_price": 210.0
    },
    {
      "sku": "BTN-STD-101",
      "name": "Standard Black Button",
      "quantity": 440,
      "unit_price": 1.5,
      "total_price": 660.0
    },
    {
      "sku": "BTN-STD-103",
      "name": "Standard Silver Button",
      "quantity": 70,
      "unit_price": 1.8,
      "total_price": 126.0
    },
    {
      "sku": "BTN-STD-102",
      "name": "Standard White Button",
      "quantity": 57,
      "unit_price": 1.5,
      "total_price": 85.5
    }
  ],
  "total_amount": 3021.0,
  "priority": 3,
  "sla_hours": 24,
  "current_state": "CLOSED",
  "created_at": 1758175619.331747,
  "history": [
    {
      "from_state": "CREATED",
      "to_state": "CREATED",
      "timestamp": 1758778620.6298544,
      "agent": "OrderSystem",
      "reason": "Order created from email/PDF",
      "metadata": {
        "source": "email_processing",
        "total_amount": 3021.0
      }
    },
    {
      "from_state": "CREATED",
      "to_state": "CONFIRMED",
      "timestamp": 1758778620.6305392,
      "agent": "SalesAgent",
      "reason": "Customer confirmed order via email",
      "metadata": {
        "simulation_generated": true,
        "timestamp": 1758183741.7598617,
        "confirmation_method": "email_reply",
        "delivery_address": "Distribution Center",
        "special_instructions": "Prototype order"
      }
    },
    {
      "from_state": "CONFIRMED",
      "to_state": "PLANNED",
      "timestamp": 1758778620.6311314,
      "agent": "ProductionPlanning",
      "reason": "Production scheduled and materials reserved",
      "metadata": {
        "simulation_generated": true,
        "timestamp": 1758200297.5047655,
        "production_slot": "2025-01-27 8:00",
        "assigned_line": "Line A",
        "estimated_duration": "11 hours"
      }
    },
    {
      "from_state": "PLANNED",
      "to_state": "IN_PRODUCTION",
      "timestamp": 1758778620.6318314,
      "agent": "ProductionAgent",
      "reason": "Manufacturing commenced",
      "metadata": {
        "simulation_generated": true,
        "timestamp": 1758331678.4203916,
        "batch_number": "BATCH_2025_367",
        "quality_inspector": "Klaus Mueller",
        "materials_reserved": true,
        "production_notes": null
      }
    },
    {
      "from_state": "IN_PRODUCTION",
      "to_state": "PRODUCED",
      "timestamp": 1758778620.6325402,
      "agent": "QualityInspector",
      "reason": "Quality inspection passed",
      "metadata": {
        "simulation_generated": true,
        "timestamp": 1758336679.5675597,
        "qa_inspector": "Andrea Wagner",
        "quality_score": "B+",
        "defect_rate": "0.056%",
        "batch_test_results": "PASSED"
      }
    },
    {
      "from_state": "PRODUCED",
      "to_state": "PACKED",
      "timestamp": 1758778620.6333115,
      "agent": "LogisticsAgent",
      "reason": "Order packed and labeled",
      "metadata": {
        "simulation_generated": true,
        "timestamp": 1758339254.7505388,
        "package_id": "PKG_2025_8677",
        "weight_kg": 32.3,
        "dimensions": "71x48x12cm",
        "packaging_type": "Protective Foam"
      }
    },
    {
      "from_state": "PACKED",
      "to_state": "SHIPPED",
      "timestamp": 1758778620.6339781,
      "agent": "ShippingCoordinator",
      "reason": "Shipped via DHL Express",
      "metadata": {
        "simulation_generated": true,
        "timestamp": 1758343481.1413925,
        "tracking_number": "DHL350010646",
        "carrier": "DHL Express",
        "shipping_cost": 54.81,
        "estimated_delivery": "2025-01-31"
      }
    },
    {
      "from_state": "SHIPPED",
      "to_state": "DELIVERED",
      "timestamp": 1758778620.6346562,
      "agent": "LogisticsAgent",
      "reason": "Delivery confirmed by recipient",
      "metadata": {
        "simulation_generated": true,
        "timestamp": 1758535761.9259958,
        "delivery_timestamp": "2025-01-30 16:45",
        "recipient": "Receiving Dept",
        "signature": "J. Mueller"
      }
    },
    {
      "from_state": "DELIVERED",
      "to_state": "INVOICED",
      "timestamp": 1758778620.6353579,
      "agent": "AccountsReceivable",
      "reason": "Invoice generated and sent",
      "metadata": {
        "simulation_generated": true,
        "timestamp": 1758598466.7837768,
        "invoice_number": "INV-2025-9216",
        "payment_terms": "Net 14",
        "discount_applied": 10
      }
    },
    {
      "from_state": "INVOICED",
      "to_state": "CLOSED",
      "timestamp": 1758778620.6360605,
      "agent": "FinanceAgent",
      "reason": "Payment received and processed",
      "metadata": {
        "simulation_generated": true,
        "timestamp": 1761147942.976176,
        "payment_date": "2025-3-05",
        "payment_method": "Wire Transfer",
        "transaction_id": "TXN_649880"
      }
    }
  ],
  "metadata": {
    "customer_type": "SME",
    "simulation_day": 24,
    "historical_seed": true,
    "original_timestamp": 1758175619.331747
  }
}