{
  "id": "ORD_1758778620_178",
  "customer_email": "purchasing@zf.com",
  "customer_name": "ZF Friedrichshafen AG",
  "items": [
    {
      "sku": "BTN-STD-101",
      "name": "Standard Black Button",
      "quantity": 1366,
      "unit_price": 1.5,
      "total_price": 2049.0
    },
    {
      "sku": "BTN-MECH-501",
      "name": "Mechanical Switch Button",
      "quantity": 91,
      "unit_price": 9.2,
      "total_price": 837.1999999999999
    },
    {
      "sku": "BTN-STD-102",
      "name": "Standard White Button",
      "quantity": 1076,
      "unit_price": 1.5,
      "total_price": 1614.0
    },
    {
      "sku": "BTN-STD-103",
      "name": "Standard Silver Button",
      "quantity": 65,
      "unit_price": 1.8,
      "total_price": 117.0
    }
  ],
  "total_amount": 4617.2,
  "priority": 3,
  "sla_hours": 24,
  "current_state": "CLOSED",
  "created_at": 1758004619.331747,
  "history": [
    {
      "from_state": "CREATED",
      "to_state": "CREATED",
      "timestamp": 1758778620.5522761,
      "agent": "OrderSystem",
      "reason": "Order created from email/PDF",
      "metadata": {
        "source": "email_processing",
        "total_amount": 4617.2
      }
    },
    {
      "from_state": "CREATED",
      "to_state": "CONFIRMED",
      "timestamp": 1758778620.5525715,
      "agent": "SalesAgent",
      "reason": "Customer confirmed order via email",
      "metadata": {
        "simulation_generated": true,
        "timestamp": 1758007216.769744,
        "confirmation_method": "portal_confirmation",
        "delivery_address": "Distribution Center",
        "special_instructions": "Quality critical"
      }
    },
    {
      "from_state": "CONFIRMED",
      "to_state": "PLANNED",
      "timestamp": 1758778620.5531213,
      "agent": "ProductionPlanning",
      "reason": "Production scheduled and materials reserved",
      "metadata": {
        "simulation_generated": true,
        "timestamp": 1758019022.9435909,
        "production_slot": "2025-01-20 14:00",
        "assigned_line": "Special Line",
        "estimated_duration": "24 hours"
      }
    },
    {
      "from_state": "PLANNED",
      "to_state": "IN_PRODUCTION",
      "timestamp": 1758778620.5536897,
      "agent": "ProductionAgent",
      "reason": "Manufacturing commenced",
      "metadata": {
        "simulation_generated": true,
        "timestamp": 1758138035.2460973,
        "batch_number": "BATCH_2025_205",
        "quality_inspector": "Hans Weber",
        "materials_reserved": true,
        "production_notes": "Extra QC required"
      }
    },
    {
      "from_state": "IN_PRODUCTION",
      "to_state": "PRODUCED",
      "timestamp": 1758778620.554259,
      "agent": "QualityInspector",
      "reason": "Quality inspection passed",
      "metadata": {
        "simulation_generated": true,
        "timestamp": 1758158318.735115,
        "qa_inspector": "Andrea Wagner",
        "quality_score": "A",
        "defect_rate": "0.091%",
        "batch_test_results": "PASSED"
      }
    },
    {
      "from_state": "PRODUCED",
      "to_state": "PACKED",
      "timestamp": 1758778620.554881,
      "agent": "LogisticsAgent",
      "reason": "Order packed and labeled",
      "metadata": {
        "simulation_generated": true,
        "timestamp": 1758161548.9686253,
        "package_id": "PKG_2025_1836",
        "weight_kg": 9.4,
        "dimensions": "73x60x28cm",
        "packaging_type": "Reinforced Box"
      }
    },
    {
      "from_state": "PACKED",
      "to_state": "SHIPPED",
      "timestamp": 1758778620.5556173,
      "agent": "ShippingCoordinator",
      "reason": "Shipped via DHL Express",
      "metadata": {
        "simulation_generated": true,
        "timestamp": 1758170638.4834957,
        "tracking_number": "DHL205782771",
        "carrier": "UPS",
        "shipping_cost": 31.41,
        "estimated_delivery": "2025-01-25"
      }
    },
    {
      "from_state": "SHIPPED",
      "to_state": "DELIVERED",
      "timestamp": 1758778620.5562363,
      "agent": "LogisticsAgent",
      "reason": "Delivery confirmed by recipient",
      "metadata": {
        "simulation_generated": true,
        "timestamp": 1758403035.6619587,
        "delivery_timestamp": "2025-01-20 14:12",
        "recipient": "Receiving Dept",
        "signature": "M. Klein"
      }
    },
    {
      "from_state": "DELIVERED",
      "to_state": "INVOICED",
      "timestamp": 1758778620.5569184,
      "agent": "AccountsReceivable",
      "reason": "Invoice generated and sent",
      "metadata": {
        "simulation_generated": true,
        "timestamp": 1758474249.8505683,
        "invoice_number": "INV-2025-9145",
        "payment_terms": "Net 7",
        "discount_applied": 0
      }
    },
    {
      "from_state": "INVOICED",
      "to_state": "CLOSED",
      "timestamp": 1758778620.5575962,
      "agent": "FinanceAgent",
      "reason": "Payment received and processed",
      "metadata": {
        "simulation_generated": true,
        "timestamp": 1759574855.4981215,
        "payment_date": "2025-2-18",
        "payment_method": "Check",
        "transaction_id": "TXN_315300"
      }
    }
  ],
  "metadata": {
    "customer_type": "Enterprise",
    "simulation_day": 22,
    "historical_seed": true,
    "original_timestamp": 1758004619.331747
  }
}